pycubelut.py
pycubelut-0.2.3.dist-info/entry_points.txt
pycubelut-0.2.3.dist-info/LICENSE
pycubelut-0.2.3.dist-info/WHEEL
pycubelut-0.2.3.dist-info/METADATA
pycubelut-0.2.3.dist-info/RECORD
