Metadata-Version: 2.1
Name: pycubelut
Version: 0.2.3
Summary: Tool for Applying Adobe Cube LUTs to Images
Home-page: https://github.com/yoonsikp/pycubelut
License: MIT
Keywords: cube,lut,cubelut,3d,python
Author: Yoonsik Park
Author-email: park.yoonsik@icloud.com
Requires-Python: >=3.5,<4.0
Classifier: License :: OSI Approved :: MIT License
Classifier: Programming Language :: Python :: 3
Classifier: Programming Language :: Python :: 3.5
Classifier: Programming Language :: Python :: 3.6
Classifier: Programming Language :: Python :: 3.7
Classifier: Programming Language :: Python :: 3.8
Requires-Dist: colour-science (>=0.3,<0.4)
Requires-Dist: numpy (>=1.18,<2.0)
Requires-Dist: pillow (>=6.2,<7.0)
Requires-Dist: scipy (>=1.4,<2.0)
Project-URL: Repository, https://github.com/yoonsikp/pycubelut
